[
    {
        "_emitter": {},
        "numOfParticlesToEmit": {
            "from": 10,
            "to": 40
        },
        "particleAngle": {
            "from": 3.59,
            "to": 5.58
        },
        "particleVelocity": {
            "from": 100,
            "to": 1000
        },
        "particleLiveTime": {
            "from": 10000,
            "to": 10000
        },
        "emissionRadius": 50,
        "type": "particleSystem",
        "name": "o",
        "_particles": [],
        "_gameObject": {
            "pos": {
                "x": 0,
                "y": 0
            },
            "vel": {
                "x": 0,
                "y": 0
            },
            "scale": {
                "x": 1,
                "y": 1
            },
            "tileOffset": {
                "x": 0,
                "y": 0
            },
            "type": "gameObject",
            "commonBehaviour": [],
            "currFrameIndex": 0,
            "frameAnimationIds": [],
            "tileRepeat": false,
            "groupName": "",
            "fixedToCamera": false,
            "rigid": false,
            "angle": 0,
            "angleVel": 0,
            "alpha": 1,
            "width": 443,
            "height": 350,
            "name": "capust",
            "spriteSheetId": "7753_0918_65",
            "id": "7906_0779_66"
        },
        "gameObjectId": "7906_0779_66",
        "id": "5397_3591_67"
    }
]